extractcode_7z/__init__.py
extractcode_7z/bin/7z.dll
extractcode_7z/bin/7z.exe
extractcode_7z/licenses/History.txt
extractcode_7z/licenses/License.txt
extractcode_7z/licenses/copying.txt
extractcode_7z/licenses/readme.txt
extractcode_7z/licenses/unRarLicense.txt
extractcode_7z-16.5.210223.dist-info/LICENSE.txt
extractcode_7z-16.5.210223.dist-info/METADATA
extractcode_7z-16.5.210223.dist-info/README.rst
extractcode_7z-16.5.210223.dist-info/WHEEL
extractcode_7z-16.5.210223.dist-info/apache-2.0.LICENSE
extractcode_7z-16.5.210223.dist-info/entry_points.txt
extractcode_7z-16.5.210223.dist-info/top_level.txt
extractcode_7z-16.5.210223.dist-info/RECORD
